etcd/__init__.py
etcd/client.py
etcd/common_ops.py
etcd/compat.py
etcd/config.py
etcd/directory_ops.py
etcd/exceptions.py
etcd/inorder_ops.py
etcd/log.py
etcd/node_ops.py
etcd/response.py
etcd/server_ops.py
etcd/stat_ops.py
etcd/modules/__init__.py
etcd/modules/leader.py
etcd/modules/lock.py
etcd-2.0.8.dist-info/DESCRIPTION.rst
etcd-2.0.8.dist-info/METADATA
etcd-2.0.8.dist-info/metadata.json
etcd-2.0.8.dist-info/RECORD
etcd-2.0.8.dist-info/top_level.txt
etcd-2.0.8.dist-info/WHEEL
